_ethash.abi3.so
ethash-0.9.0.dist-info/LICENSE
ethash-0.9.0.dist-info/METADATA
ethash-0.9.0.dist-info/WHEEL
ethash-0.9.0.dist-info/top_level.txt
ethash-0.9.0.dist-info/RECORD
