Metadata-Version: 2.1
Name: ethash
Version: 0.9.0
Summary: C/C++ implementation of Ethash – the Ethereum Proof of Work algorithm
Home-page: https://github.com/chfast/ethash
Author: Paweł Bylica
Author-email: pawel@ethereum.org
License: Apache License, Version 2.0
Platform: UNKNOWN
Classifier: License :: OSI Approved :: Apache Software License
Classifier: Programming Language :: C
Classifier: Programming Language :: C++
Classifier: Programming Language :: Python :: 3
Classifier: Programming Language :: Python :: 3.6
Classifier: Programming Language :: Python :: 3.7
Classifier: Programming Language :: Python :: 3.8
Classifier: Programming Language :: Python :: 3.9
Requires-Python: >=3.6
Requires-Dist: cffi (>=1.12)
